strucgap/__init__.py
strucgap/datavisualization.py
strucgap/functionannotation.py
strucgap/glycanstructure.py
strucgap/glyconetwork.py
strucgap/glycopeptidequant.py
strucgap/glycosite.py
strucgap/insighttracker.py
strucgap/preprocess.py
strucgap/test.py
strucgap-1.1.4.dist-info/METADATA
strucgap-1.1.4.dist-info/WHEEL
strucgap-1.1.4.dist-info/top_level.txt
strucgap-1.1.4.dist-info/RECORD
